{"chunk_definitions":[{"row":21,"row_count":1,"visible":true,"expansion_state":0,"options":{"engine":"r","label":"setup","include":false,"dev":"png"},"document_id":"95EBCC4E","chunk_id":"csetup_chunk","chunk_label":"setup"},{"row":32,"row_count":1,"visible":true,"expansion_state":0,"options":{"engine":"css","echo":false,"label":"unnamed-chunk-1","dev":"png"},"document_id":"95EBCC4E","chunk_id":"cw9ov1rgqbwb8","chunk_label":"unnamed-chunk-1"},{"row":36,"row_count":1,"visible":true,"expansion_state":0,"options":{"engine":"r","warning":false,"message":false,"include":false,"echo":false,"label":"unnamed-chunk-2","dev":"png"},"document_id":"95EBCC4E","chunk_id":"c2flo3kyoe134","chunk_label":"unnamed-chunk-2"},{"row":56,"row_count":1,"visible":true,"expansion_state":0,"options":{"engine":"r","label":"load libraries","warning":false,"message":false,"dev":"png"},"document_id":"95EBCC4E","chunk_id":"ce9oay9qer80m","chunk_label":"load libraries"},{"row":68,"row_count":1,"visible":true,"expansion_state":0,"options":{"engine":"r","label":"figure settings","echo":false,"dev":"png"},"document_id":"95EBCC4E","chunk_id":"c03b4xtd5hytr","chunk_label":"figure settings"},{"row":78,"row_count":1,"visible":true,"expansion_state":0,"options":{"engine":"r","label":"load data","message":false,"dev":"png"},"document_id":"95EBCC4E","chunk_id":"cot0ypahvnu0b","chunk_label":"load data"},{"row":86,"row_count":1,"visible":true,"expansion_state":0,"options":{"engine":"r","label":"clean up data","dev":"png"},"document_id":"95EBCC4E","chunk_id":"cvt9e5oheb4l3","chunk_label":"clean up data"}],"doc_write_time":1704897421,"working_dir":null,"default_chunk_options":{"echo":true,"fig.align":"center","fig.width":12.0,"fig.height":8.0}}